verify/stimulus_src/counter_fsm.v
// counter_fsm.v — a free-running counter driving a small FSM, with a few
// multi-bit buses. Exercises: scalar toggling (clk/rst), vector values
// (counter, state), rise/fall edge counting, static signals.
`timescale 1ns/1ps
module counter_fsm;
  reg        clk;
  reg        rst_n;
  reg  [7:0] counter;
  reg  [2:0] state;
  reg  [15:0] accum;
  wire       tick;
  reg        enable;
  reg  [3:0] const_cfg;   // set once, then static

  localparam S_IDLE = 3'd0, S_RUN = 3'd1, S_HOLD = 3'd2, S_DONE = 3'd3;

  assign tick = (counter == 8'hFF);

  // clock: 10ns period
  initial begin
    clk = 1'b0;
    forever #5 clk = ~clk;
  end

  initial begin
    $dumpfile("counter_fsm.vcd");
    $dumpvars(0, counter_fsm);
    rst_n     = 1'b0;
    counter   = 8'h00;
    state     = S_IDLE;
    accum     = 16'h0000;
    enable    = 1'b0;
    const_cfg = 4'hA;     // becomes static after t=0

    #12 rst_n  = 1'b1;
    #8  enable = 1'b1;

    // run for a while
    #400 enable = 1'b0;
    #40  $finish;
  end

  // counter
  always @(posedge clk) begin
    if (!rst_n)      counter <= 8'h00;
    else if (enable) counter <= counter + 8'd1;
  end

  // accumulator (wider bus, changes less often)
  always @(posedge clk) begin
    if (!rst_n)            accum <= 16'h0000;
    else if (enable && counter[1:0] == 2'b00)
                           accum <= accum + 16'd7;
  end

  // simple FSM
  always @(posedge clk) begin
    if (!rst_n) state <= S_IDLE;
    else begin
      case (state)
        S_IDLE: if (enable)        state <= S_RUN;
        S_RUN:  if (counter > 8'd200) state <= S_HOLD;
        S_HOLD: if (tick)          state <= S_DONE;
        S_DONE:                    state <= S_IDLE;
        default:                   state <= S_IDLE;
      endcase
    end
  end
endmodule

verify/stimulus/counter_fsm.vcd
$date
    1970-01-01 00:00:00 UTC
$end
$version
    rwave-stimulus
$end
$timescale
	1ps
$end
$scope module counter_fsm $end
$var wire 1 ! tick $end
$var parameter 3 " S_DONE $end
$var parameter 3 # S_HOLD $end
$var parameter 3 $ S_IDLE $end
$var parameter 3 % S_RUN $end
$var reg 16 & accum [15:0] $end
$var reg 1 ' clk $end
$var reg 4 ( const_cfg [3:0] $end
$var reg 8 ) counter [7:0] $end
$var reg 1 * enable $end
$var reg 1 + rst_n $end
$var reg 3 , state [2:0] $end
$upscope $end
$enddefinitions $end
$comment Show the parameter values. $end
$dumpall
b1 %
b0 $
b10 #
b11 "
$end
#0
$dumpvars
b0 ,
0+
0*
b0 )
b1010 (
0'
b0 &
0!
$end
#5000
1'
#10000
0'
#12000
1+
#15000
1'
#20000
0'
1*
#25000
b1 )
b111 &
b1 ,
1'
#30000
0'
#35000
b10 )
1'
#40000
0'
#45000
b11 )
1'
#50000
0'
#55000
b100 )
1'
#60000
0'
#65000
b101 )
b1110 &
1'
#70000
0'
#75000
b110 )
1'
#80000
0'
#85000
b111 )
1'
#90000
0'
#95000
b1000 )
1'
#100000
0'
#105000
b1001 )
b10101 &
1'
#110000
0'
#115000
b1010 )
1'
#120000
0'
#125000
b1011 )
1'
#130000
0'
#135000
b1100 )
1'
#140000
0'
#145000
b1101 )
b11100 &
1'
#150000
0'
#155000
b1110 )
1'
#160000
0'
#165000
b1111 )
1'
#170000
0'
#175000
b10000 )
1'
#180000
0'
#185000
b10001 )
b100011 &
1'
#190000
0'
#195000
b10010 )
1'
#200000
0'
#205000
b10011 )
1'
#210000
0'
#215000
b10100 )
1'
#220000
0'
#225000
b10101 )
b101010 &
1'
#230000
0'
#235000
b10110 )
1'
#240000
0'
#245000
b10111 )
1'
#250000
0'
#255000
b11000 )
1'
#260000
0'
#265000
b11001 )
b110001 &
1'
#270000
0'
#275000
b11010 )
1'
#280000
0'
#285000
b11011 )
1'
#290000
0'
#295000
b11100 )
1'
#300000
0'
#305000
b11101 )
b111000 &
1'
#310000
0'
#315000
b11110 )
1'
#320000
0'
#325000
b11111 )
1'
#330000
0'
#335000
b100000 )
1'
#340000
0'
#345000
b100001 )
b111111 &
1'
#350000
0'
#355000
b100010 )
1'
#360000
0'
#365000
b100011 )
1'
#370000
0'
#375000
b100100 )
1'
#380000
0'
#385000
b100101 )
b1000110 &
1'
#390000
0'
#395000
b100110 )
1'
#400000
0'
#405000
b100111 )
1'
#410000
0'
#415000
b101000 )
1'
#420000
0'
0*
