verify/stimulus_src/edge_cases.v
// Adapted from OpenWaveAnalyzer (github.com/neveltyc/OpenWaveAnalyzer),
// verify/designs/edge_cases.v — used here to exercise edge-case value formatting
// (wide all-z/all-x buses, 1-bit [0:0] selects, static signals).

module edge_cases;
  reg clk = 0;
  reg rst_n = 0;
  reg toggle_1 = 0;
  reg toggle_fast = 0;
  reg [0:0] one_bit_bus = 0;
  reg [2:0] three_bit = 3'b000;
  reg static_high = 1;
  reg static_low = 0;

  always #5 clk = ~clk;
  always #10 toggle_fast = ~toggle_fast;

  initial begin
    $dumpfile("edge_cases.vcd");
    $dumpvars(0, edge_cases);
    #2 rst_n = 1;
    #10 toggle_1 = 1;
    #20 toggle_1 = 0;
    #10 toggle_1 = 1;
    #5 toggle_1 = 0;
    #15 three_bit = 3'b101;
    #10 three_bit = 3'b010;
    #10 one_bit_bus = 1;
    #10 one_bit_bus = 0;
    #10 three_bit = 3'b111;
    #20 $finish;
  end
endmodule

verify/stimulus/edge_cases.vcd
$date
	Sat May 30 09:44:46 2026
$end
$version
	Icarus Verilog
$end
$timescale
	1s
$end
$scope module edge_cases $end
$var reg 1 ! clk $end
$var reg 1 " one_bit_bus $end
$var reg 1 # rst_n $end
$var reg 1 $ static_high $end
$var reg 1 % static_low $end
$var reg 3 & three_bit [2:0] $end
$var reg 1 ' toggle_1 $end
$var reg 1 ( toggle_fast $end
$upscope $end
$enddefinitions $end
$comment Show the parameter values. $end
$dumpall
$end
#0
$dumpvars
0(
0'
b0 &
0%
1$
0#
0"
0!
$end
#2
1#
#5
1!
#10
0!
1(
#12
1'
#15
1!
#20
0!
0(
#25
1!
#30
0!
1(
#32
0'
#35
1!
#40
0!
0(
#42
1'
#45
1!
#47
0'
#50
0!
1(
#55
1!
#60
0!
0(
#62
b101 &
#65
1!
#70
0!
1(
#72
b10 &
#75
1!
#80
0!
0(
#82
1"
#85
1!
#90
0!
1(
#92
0"
#95
1!
#100
0!
0(
#102
b111 &
#105
1!
#110
0!
1(
#115
1!
#120
0!
0(
