verify/stimulus_src/handshake_proto.v
// handshake_proto.v — a valid/ready data handshake with back-pressure. Built
// to exercise `search`: interval mode (valid=1), segment mode (--show data),
// event mode (--changed data), and multi-condition (valid=1,ready=1).
`timescale 1ns/1ps
module handshake_proto;
  reg        clk;
  reg        rst_n;
  reg        valid;
  reg        ready;
  reg  [7:0] data;
  wire       fire;          // a beat completes when valid & ready
  reg  [7:0] beats;         // count of completed transfers

  assign fire = valid & ready;

  initial begin
    $dumpfile("handshake_proto.vcd");
    $dumpvars(0, handshake_proto);
    clk = 0; rst_n = 0; valid = 0; ready = 0; data = 8'h00; beats = 8'h00;
    #12 rst_n = 1;

    // sender presents data
    #8  valid = 1; data = 8'h10;
    #10 ready = 1;             // first beat fires
    #10 data  = 8'h20;         // next word while ready high
    #10 ready = 0;             // back-pressure
    #20 ready = 1;             // resume
    #10 valid = 0;             // sender idle
    #10 valid = 1; data = 8'h30;
    #10 data  = 8'h31;
    #10 valid = 0; ready = 0;
    #20 $finish;
  end

  always #5 clk = ~clk;

  always @(posedge clk) begin
    if (!rst_n) beats <= 8'h00;
    else if (fire) beats <= beats + 8'd1;
  end
endmodule

verify/stimulus/handshake_proto.vcd
$date
	Fri May 29 23:12:26 2026
$end
$version
	Icarus Verilog
$end
$timescale
	1ps
$end
$scope module handshake_proto $end
$var wire 1 ! fire $end
$var reg 8 " beats [7:0] $end
$var reg 1 # clk $end
$var reg 8 $ data [7:0] $end
$var reg 1 % ready $end
$var reg 1 & rst_n $end
$var reg 1 ' valid $end
$upscope $end
$enddefinitions $end
$comment Show the parameter values. $end
$dumpall
$end
#0
$dumpvars
0'
0&
0%
b0 $
0#
b0 "
0!
$end
#5000
1#
#10000
0#
#12000
1&
#15000
1#
#20000
0#
b10000 $
1'
#25000
1#
#30000
1!
0#
1%
#35000
b1 "
1#
#40000
0#
b100000 $
#45000
b10 "
1#
#50000
0!
0#
0%
#55000
1#
#60000
0#
#65000
1#
#70000
1!
0#
1%
#75000
b11 "
1#
#80000
0!
0#
0'
#85000
1#
#90000
1!
0#
b110000 $
1'
#95000
b100 "
1#
#100000
0#
b110001 $
#105000
b101 "
1#
#110000
0!
0#
0%
0'
