verify/stimulus_src/hier_deep.v
// hier_deep.v — a nested module hierarchy so the analyzer sees several scopes
// at different depths. Exercises scope enumeration in `info`, path prefixes in
// `list --filter`, and signals that alias across instances.
`timescale 1ns/1ps

module leaf(input wire clk, input wire en, output reg [3:0] cnt);
  initial cnt = 4'h0;
  always @(posedge clk) if (en) cnt <= cnt + 4'd1;
endmodule

module mid(input wire clk, input wire en, output wire [3:0] a, output wire [3:0] b);
  leaf u_a(.clk(clk), .en(en),       .cnt(a));
  leaf u_b(.clk(clk), .en(en & a[0]), .cnt(b));
endmodule

module hier_deep;
  reg clk, en;
  wire [3:0] m0_a, m0_b, m1_a, m1_b;

  mid u_m0(.clk(clk), .en(en),        .a(m0_a), .b(m0_b));
  mid u_m1(.clk(clk), .en(en & m0_b[1]), .a(m1_a), .b(m1_b));

  initial begin
    $dumpfile("hier_deep.vcd");
    $dumpvars(0, hier_deep);
    clk = 1'b0; en = 1'b0;
    #7 en = 1'b1;
    #300 $finish;
  end
  always #5 clk = ~clk;
endmodule

verify/stimulus/hier_deep.vcd
$date
    1970-01-01 00:00:00 UTC
$end
$version
    rwave-stimulus
$end
$timescale
	1ps
$end
$scope module hier_deep $end
$var wire 4 ! m1_b [3:0] $end
$var wire 4 " m1_a [3:0] $end
$var wire 4 # m0_b [3:0] $end
$var wire 4 $ m0_a [3:0] $end
$var reg 1 % clk $end
$var reg 1 & en $end
$scope module u_m0 $end
$var wire 1 % clk $end
$var wire 1 & en $end
$var wire 4 ' b [3:0] $end
$var wire 4 ( a [3:0] $end
$scope module u_a $end
$var wire 1 % clk $end
$var wire 1 & en $end
$var reg 4 ) cnt [3:0] $end
$upscope $end
$scope module u_b $end
$var wire 1 % clk $end
$var wire 1 * en $end
$var reg 4 + cnt [3:0] $end
$upscope $end
$upscope $end
$scope module u_m1 $end
$var wire 1 % clk $end
$var wire 1 , en $end
$var wire 4 - b [3:0] $end
$var wire 4 . a [3:0] $end
$scope module u_a $end
$var wire 1 % clk $end
$var wire 1 , en $end
$var reg 4 / cnt [3:0] $end
$upscope $end
$scope module u_b $end
$var wire 1 % clk $end
$var wire 1 0 en $end
$var reg 4 1 cnt [3:0] $end
$upscope $end
$upscope $end
$upscope $end
$enddefinitions $end
$comment Show the parameter values. $end
$dumpall
$end
#0
$dumpvars
b0 1
00
b0 /
b0 .
b0 -
0,
b0 +
0*
b0 )
b0 (
b0 '
0&
0%
b0 $
b0 #
b0 "
b0 !
$end
#5000
1%
#7000
1&
#10000
0%
#15000
1*
b1 $
b1 (
b1 )
1%
#20000
0%
#25000
0*
b10 $
b10 (
b10 )
b1 #
b1 '
b1 +
1%
#30000
0%
#35000
1*
b11 $
b11 (
b11 )
1%
#40000
0%
#45000
0*
1,
b100 $
b100 (
b100 )
b10 #
b10 '
b10 +
1%
#50000
0%
#55000
10
1*
b1 "
b1 .
b1 /
b101 $
b101 (
b101 )
1%
#60000
0%
#65000
0*
00
b110 $
b110 (
b110 )
b11 #
b11 '
b11 +
b10 "
b10 .
b10 /
b1 !
b1 -
b1 1
1%
#70000
0%
#75000
10
1*
b11 "
b11 .
b11 /
b111 $
b111 (
b111 )
1%
#80000
0%
#85000
0*
0,
00
b1000 $
b1000 (
b1000 )
b100 #
b100 '
b100 +
b100 "
b100 .
b100 /
b10 !
b10 -
b10 1
1%
#90000
0%
#95000
1*
b1001 $
b1001 (
b1001 )
1%
#100000
0%
#105000
0*
b1010 $
b1010 (
b1010 )
b101 #
b101 '
b101 +
1%
#110000
0%
#115000
1*
b1011 $
b1011 (
b1011 )
1%
#120000
0%
#125000
0*
1,
b1100 $
b1100 (
b1100 )
b110 #
b110 '
b110 +
1%
#130000
0%
#135000
10
1*
b101 "
b101 .
b101 /
b1101 $
b1101 (
b1101 )
1%
#140000
0%
#145000
0*
00
b1110 $
b1110 (
b1110 )
b111 #
b111 '
b111 +
b110 "
b110 .
b110 /
b11 !
b11 -
b11 1
1%
#150000
0%
#155000
10
1*
b111 "
b111 .
b111 /
b1111 $
b1111 (
b1111 )
1%
#160000
0%
#165000
0*
0,
00
b0 $
b0 (
b0 )
b1000 #
b1000 '
b1000 +
b1000 "
b1000 .
b1000 /
b100 !
b100 -
b100 1
1%
#170000
0%
#175000
1*
b1 $
b1 (
b1 )
1%
#180000
0%
#185000
0*
b10 $
b10 (
b10 )
b1001 #
b1001 '
b1001 +
1%
#190000
0%
#195000
1*
b11 $
b11 (
b11 )
1%
#200000
0%
#205000
0*
1,
b100 $
b100 (
b100 )
b1010 #
b1010 '
b1010 +
1%
#210000
0%
#215000
10
1*
b1001 "
b1001 .
b1001 /
b101 $
b101 (
b101 )
1%
#220000
0%
#225000
0*
00
b110 $
b110 (
b110 )
b1011 #
b1011 '
b1011 +
b1010 "
b1010 .
b1010 /
b101 !
b101 -
b101 1
1%
#230000
0%
#235000
10
1*
b1011 "
b1011 .
b1011 /
b111 $
b111 (
b111 )
1%
#240000
0%
#245000
0*
0,
00
b1000 $
b1000 (
b1000 )
b1100 #
b1100 '
b1100 +
b1100 "
b1100 .
b1100 /
b110 !
b110 -
b110 1
1%
#250000
0%
#255000
1*
b1001 $
b1001 (
b1001 )
1%
#260000
0%
#265000
0*
b1010 $
b1010 (
b1010 )
b1101 #
b1101 '
b1101 +
1%
#270000
0%
#275000
1*
b1011 $
b1011 (
b1011 )
1%
#280000
0%
#285000
0*
1,
b1100 $
b1100 (
b1100 )
b1110 #
b1110 '
b1110 +
1%
#290000
0%
#295000
10
1*
b1101 "
b1101 .
b1101 /
b1101 $
b1101 (
b1101 )
1%
#300000
0%
#305000
0*
00
b1110 $
b1110 (
b1110 )
b1111 #
b1111 '
b1111 +
b1110 "
b1110 .
b1110 /
b111 !
b111 -
b111 1
1%
