verify/stimulus_src/real_event.v
// real_event.v — exercises non-logic value kinds: `real` variables (printed
// verbatim) and a Verilog `event`, plus a wide 64-bit vector to test bignum
// decimal/hex formatting in fmt_val.
`timescale 1ns/1ps
module real_event;
  real        voltage;
  real        temperature;
  reg  [63:0] wide;
  event       sample;       // named event
  reg         sampled;
  integer     i;

  initial begin
    $dumpfile("real_event.vcd");
    $dumpvars(0, real_event);
    voltage     = 0.0;
    temperature = 25.5;
    wide        = 64'h0000_0000_0000_0000;
    sampled     = 1'b0;

    for (i = 0; i < 8; i = i + 1) begin
      #10;
      voltage     = voltage + 0.25;
      temperature = temperature - 0.5;
      wide        = wide + 64'h0011_2233_4455_6677;
      ->sample;                 // trigger the event
      sampled     = ~sampled;
    end
    #10 $finish;
  end
endmodule

verify/stimulus/real_event.vcd
$date
	Fri May 29 23:12:26 2026
$end
$version
	Icarus Verilog
$end
$timescale
	1ps
$end
$scope module real_event $end
$var event 1 ! sample $end
$var reg 1 " sampled $end
$var reg 64 # wide [63:0] $end
$var integer 32 $ i [31:0] $end
$var real 1 % temperature $end
$var real 1 & voltage $end
$upscope $end
$enddefinitions $end
$comment Show the parameter values. $end
$dumpall
$end
#0
$dumpvars
r0 &
r25.5 %
b0 $
b0 #
0"
1!
$end
#10000
b1 $
1"
1!
b10001001000100011001101000100010101010110011001110111 #
r25 %
r0.25 &
#20000
b10 $
0"
1!
b100010010001000110011010001000101010101100110011101110 #
r24.5 %
r0.5 &
#30000
b11 $
1"
1!
b110011011001101001100111001101000000000011001101100101 #
r24 %
r0.75 &
#40000
b100 $
0"
1!
b1000100100010001100110100010001010101011001100111011100 #
r23.5 %
r1 &
#50000
b101 $
1"
1!
b1010101101010110000000001010101101010110000000001010011 #
r23 %
r1.25 &
#60000
b110 $
0"
1!
b1100110110011010011001110011010000000000110011011001010 #
r22.5 %
r1.5 &
#70000
b111 $
1"
1!
b1110111111011110110011011011110010101011100110101000001 #
r22 %
r1.75 &
#80000
b1000 $
0"
1!
b10001001000100011001101000100010101010110011001110111000 #
r21.5 %
r2 &
